tqdm-stubs/__init__.pyi
tqdm-stubs/py.typed
tqdm_stubs-0.2.1.dist-info/LICENSE
tqdm_stubs-0.2.1.dist-info/WHEEL
tqdm_stubs-0.2.1.dist-info/METADATA
tqdm_stubs-0.2.1.dist-info/RECORD
