Metadata-Version: 2.1
Name: tqdm-stubs
Version: 0.2.1
Summary: Stub type files for tqdm
Home-page: https://github.com/charmoniumQ/tqdm-stubs
License: MIT
Keywords: tqdm,type,stubs
Author: Samuel Grayson
Author-email: sam+dev@samgrayson.me
Requires-Python: >=3.7,<4.0
Classifier: Development Status :: 4 - Beta
Classifier: Intended Audience :: Developers
Classifier: License :: OSI Approved :: MIT License
Classifier: Natural Language :: English
Classifier: Operating System :: OS Independent
Classifier: Programming Language :: Python :: 3
Classifier: Programming Language :: Python :: 3.10
Classifier: Programming Language :: Python :: 3.7
Classifier: Programming Language :: Python :: 3.8
Classifier: Programming Language :: Python :: 3.9
Classifier: Topic :: Software Development :: Libraries :: Python Modules
Classifier: Typing :: Typed
Project-URL: Repository, https://github.com/charmoniumQ/tqdm-stubs
